geobench/__init__.py
geobench/baseline_results.ipynb
geobench/config.py
geobench/dataset.py
geobench/example_load_datasets.py
geobench/geobench_download.py
geobench/label.py
geobench/plot_tools.py
geobench/task.py
geobench/tests/launch_pytest.py
geobench/tests/test_dataset.py
geobench/tests/test_download_geobench.py
geobench/tests/test_example_load_dataset.py
geobench/torch_toolbox/__init__.py
geobench/torch_toolbox/dataset.py
geo_benchmark-0.0.8.dist-info/entry_points.txt
geo_benchmark-0.0.8.dist-info/WHEEL
geo_benchmark-0.0.8.dist-info/LICENSE
geo_benchmark-0.0.8.dist-info/METADATA
geo_benchmark-0.0.8.dist-info/RECORD
