Metadata-Version: 2.1
Name: geo-benchmark
Version: 0.0.8
Summary: A benchmark designed to advance foundation models for Earth monitoring, tailored for remote sensing. It encompasses six classification and six segmentation tasks, curated for precision and model evaluation. The package also features a comprehensive evaluation methodology and showcases results from 20 established baseline models.
License: Apache-2.0
Author: Alexandre Lacoste
Author-email: alexandre.lacoste@servicenow.com
Requires-Python: >=3.9.0,<4
Classifier: License :: OSI Approved :: Apache Software License
Classifier: Programming Language :: Python :: 3
Classifier: Programming Language :: Python :: 3.9
Classifier: Programming Language :: Python :: 3.10
Classifier: Programming Language :: Python :: 3.11
Requires-Dist: h5py (>=3.8.0,<4.0.0)
Requires-Dist: pandas (>=1.5.3,<2.0.0)
Requires-Dist: rasterio (>=1.3.8,<2.0.0)
Requires-Dist: requests (>=2.26.0,<3.0.0)
Requires-Dist: scipy (>=1.11.2,<2.0.0)
Requires-Dist: seaborn (>=0.12.2,<0.13.0)
Requires-Dist: tqdm (>=4.65.0,<5.0.0)
